phis_config/__init__.py
phis_config/common.py
phis_config/config.py
phis_config/config_class.py
phis_config/config_v2.py
phis_config-2025.8.5.0.dist-info/METADATA
phis_config-2025.8.5.0.dist-info/WHEEL
phis_config-2025.8.5.0.dist-info/licenses/LICENSE
phis_config-2025.8.5.0.dist-info/RECORD
