Metadata-Version: 2.4
Name: phis-config
Version: 2025.8.5.0
Summary: read and parse configuration file for phis-related projects
License-File: LICENSE
Requires-Python: >=3.11
